gh_oauth_helper/__init__.py
gh_oauth_helper/cli.py
gh_oauth_helper/core.py
gh_oauth_helper-0.1.1.dist-info/METADATA
gh_oauth_helper-0.1.1.dist-info/WHEEL
gh_oauth_helper-0.1.1.dist-info/entry_points.txt
gh_oauth_helper-0.1.1.dist-info/licenses/LICENSE
gh_oauth_helper-0.1.1.dist-info/RECORD
