Metadata-Version: 2.4
Name: gh-oauth-helper
Version: 0.1.1
Summary: A Python helper package for Local GitHub OAuth authentication
Project-URL: Homepage, https://github.com/jondmarien/gh-oauth-helper
Project-URL: Documentation, https://gh-oauth-helper.readthedocs.io
Project-URL: Repository, https://github.com/jondmarien/gh-oauth-helper.git
Project-URL: Bug Tracker, https://github.com/jondmarien/gh-oauth-helper/issues
Author-email: Jonathan Marien <jon@chron0.tech>
License-Expression: MIT
License-File: LICENSE
Keywords: api,authentication,github,oauth
Classifier: Development Status :: 3 - Alpha
Classifier: Intended Audience :: Developers
Classifier: License :: OSI Approved :: MIT License
Classifier: Operating System :: OS Independent
Classifier: Programming Language :: Python :: 3
Classifier: Programming Language :: Python :: 3.8
Classifier: Programming Language :: Python :: 3.9
Classifier: Programming Language :: Python :: 3.10
Classifier: Programming Language :: Python :: 3.11
Classifier: Programming Language :: Python :: 3.12
Classifier: Topic :: Internet :: WWW/HTTP :: Dynamic Content
Classifier: Topic :: Software Development :: Libraries :: Python Modules
Requires-Python: >=3.8
Requires-Dist: autopep8>=2.0.0
Requires-Dist: colorama>=0.4.4
Requires-Dist: requests-oauthlib>=1.3.0
Requires-Dist: requests>=2.25.0
Requires-Dist: rich>=13.0.0
Requires-Dist: ruff>=0.12.0
Requires-Dist: urllib3>=1.26.0
Provides-Extra: dev
Requires-Dist: black>=21.0.0; extra == 'dev'
Requires-Dist: flake8>=3.8.0; extra == 'dev'
Requires-Dist: isort>=5.0.0; extra == 'dev'
Requires-Dist: mypy>=0.812; extra == 'dev'
Requires-Dist: pytest-cov>=2.10.0; extra == 'dev'
Requires-Dist: pytest>=6.0.0; extra == 'dev'
Provides-Extra: docs
Requires-Dist: linkify-it-py>=2.0.0; extra == 'docs'
Requires-Dist: myst-parser>=0.18.0; extra == 'docs'
Requires-Dist: sphinx-rtd-theme>=1.3.0; extra == 'docs'
Requires-Dist: sphinx>=4.0.0; extra == 'docs'
